setup.py
skyhigh1312_probability/Binomialdistribution.py
skyhigh1312_probability/Gaussiandistribution.py
skyhigh1312_probability/Generaldistribution.py
skyhigh1312_probability/__init__.py
skyhigh1312_probability.egg-info/PKG-INFO
skyhigh1312_probability.egg-info/SOURCES.txt
skyhigh1312_probability.egg-info/dependency_links.txt
skyhigh1312_probability.egg-info/not-zip-safe
skyhigh1312_probability.egg-info/top_level.txt