Metadata-Version: 1.0
Name: skyhigh1312-probability
Version: 1.0
Summary: Gaussian & Binomial distributions
Home-page: UNKNOWN
Author: Sukesh Seth
Author-email: myemail@something.com
License: UNKNOWN
Platform: UNKNOWN
